pdfsearcher/__init__.py
pdfsearcher/_cli.py
pdfsearcher/_pdf_searcher.py
pdfsearcher-0.1a1.dist-info/LICENSE
pdfsearcher-0.1a1.dist-info/METADATA
pdfsearcher-0.1a1.dist-info/WHEEL
pdfsearcher-0.1a1.dist-info/entry_points.txt
pdfsearcher-0.1a1.dist-info/top_level.txt
pdfsearcher-0.1a1.dist-info/RECORD
